[
    {
        "question": "如下有一道题目，请一题多解该题目，每个解之间请只用换行符分开，并在开头注明解法几：\n已知集合M={x|-4<x<2}，N={x|x^2-x-6< 0}，则M∩N = () A．{x|-4<x<3}\tB．{x|-4<x< 2}\tC．{x|-2<x<2}\tD．{x|2<x<3}  ",
        "answer": [
            "解法一：\n1.  解决集合N：\n    *  求解不等式x² - x - 6 < 0的解集。\n    *  因式分解得到(x - 3)(x + 2) < 0。\n    *  找到根为 -2 和 3 的线性函数的图形，由于系数为正，开口向上，因此不等式的解集为 -2 < x < 3。\n\n2.  求解M ∩ N：\n    *  找出集合M和N中同时满足条件的元素。\n    *  M = {-4 < x < 2} 且 N = {-2 < x < 3}，它们的交集为 -2 < x < 2。",
            "解法二：\n1.  找出M的元素范围：-4 < x < 2\n2.  找出N的元素范围：-2 < x < 3\n3.  根据范围，M和N的交集为 -2 < x < 2\n\n\n\n因此，正确答案是 **C. {x|-2<x<2}**。"
        ],
        "response": "解法一：\n1.  解决集合N：\n    *  求解不等式x² - x - 6 < 0的解集。\n    *  因式分解得到(x - 3)(x + 2) < 0。\n    *  找到根为 -2 和 3 的线性函数的图形，由于系数为正，开口向上，因此不等式的解集为 -2 < x < 3。\n\n2.  求解M ∩ N：\n    *  找出集合M和N中同时满足条件的元素。\n    *  M = {-4 < x < 2} 且 N = {-2 < x < 3}，它们的交集为 -2 < x < 2。\n\n解法二：\n1.  找出M的元素范围：-4 < x < 2\n2.  找出N的元素范围：-2 < x < 3\n3.  根据范围，M和N的交集为 -2 < x < 2\n\n\n\n因此，正确答案是 **C. {x|-2<x<2}**。",
        "response_time": 3.752662181854248,
        "id": 1,
        "num": 2
    },
    {
        "question": "如下有一道题目，请一题多解该题目，每个解之间请只用换行符分开，并在开头注明解法几：\n古希腊时期，人们认为最美人体的头顶至肚脐的长度与肚脐至足底的长度之比是:$a = \\log_{2} 0.2$,b=2^0.2,c=0.2^0.3（a<b<c≈0.618，称为黄金分割比例)，著名的“断臂维纳斯”便是如此．此外，最美人体的头顶至咽喉的长度与咽喉至肚脐的长度之比也是a<c<b．若某人满足上述两个黄金分割比例，且腿长为105 cm，头顶至脖子下端的长度为26 cm，则其身高可能是A. 165 cm B. 175 cm C. 185 cm D. 190cm",
        "answer": [
            "解法一：\n\n设头顶至肚脐的长度为  x cm \n那么，\n\n颈至肚脐的长度为  $\\frac{x}{a}$ cm \n\n颈至肚脐长度和头顶至肚脐长度之和即为身高：\n\n $x+\\frac{x}{a}=105+\\frac{26}{a}$\n\n解得： $x=\\frac{105a+26}{a+1}$",
            "解法二：\n\n设头顶至肚脐的长度为  $x$ cm， \n\n则颈至肚脐的长度为 $\\frac{x}{a}$ cm\n\n  由于腿长为 105 cm， \n \n  所以头顶至脚端的长度为 $x+\\frac{x}{a}$\n\n  又 ，头顶至脖子下端的长度为 26cm,  所以 颈至脚端的长度为 $x+\\frac{x}{a}-26$\n\n  因此有： $x+\\frac{x}{a}-26=105$\n\n   解得： $x=\\frac{131a}{a+1}$\n\n当然不同的解法可能得到不同的表达式， \n\n最终只要通过 a 的值代入 求出 x 即为所需长度。"
        ],
        "response": "解法一：\n\n设头顶至肚脐的长度为  x cm \n那么，\n\n颈至肚脐的长度为  $\\frac{x}{a}$ cm \n\n颈至肚脐长度和头顶至肚脐长度之和即为身高：\n\n $x+\\frac{x}{a}=105+\\frac{26}{a}$\n\n解得： $x=\\frac{105a+26}{a+1}$\n\n   \n解法二：\n\n设头顶至肚脐的长度为  $x$ cm， \n\n则颈至肚脐的长度为 $\\frac{x}{a}$ cm\n\n  由于腿长为 105 cm， \n \n  所以头顶至脚端的长度为 $x+\\frac{x}{a}$\n\n  又 ，头顶至脖子下端的长度为 26cm,  所以 颈至脚端的长度为 $x+\\frac{x}{a}-26$\n\n  因此有： $x+\\frac{x}{a}-26=105$\n\n   解得： $x=\\frac{131a}{a+1}$\n\n当然不同的解法可能得到不同的表达式， \n\n最终只要通过 a 的值代入 求出 x 即为所需长度。\n\n\n\n",
        "response_time": 4.169224739074707,
        "id": 2,
        "num": 2
    },
    {
        "question": "如下有一道题目，请一题多解该题目，每个解之间请只用换行符分开，并在开头注明解法几：\n已知椭圆 \\( C \\) 的焦点为 \\( F_1(-1,0)，F_2(1,0) $，过 \\( F_2 $ 的直线与 \\( C $ 交于 \\( A $，$ B $ 两点．若 \\( |AF_2| = 2|F_2B| $，\\( |AB| = |BF_1| $，则 \\( C $ 的方程为\n\\[ \\begin{cases}\n    \\frac{x^2}{2} + y^2 = 1 \\\\\n    \\frac{x^2}{3} + \\frac{y^2}{2} \\\\\n    \\frac{x^2}{4} + \\frac{y^2}{3} \\\\\n    \\frac{x^2}{5} + \\frac{y^2}{4}\n\\end{cases} \\]\nA．$\\frac{x^2}{2} + y^2 = 1$ & B．$\\frac{x^2}{3} + \\frac{y^2}{2}$ & C．$\\frac{x^2}{4} + \\frac{y^2}{3}$ & D．$\\frac{x^2}{5} + \\frac{y^2}{4}$\"\n",
        "answer": [
            "解法一：\n设椭圆的中心为 \\( O \\)，半长轴为 \\( a \\)，半短轴为 \\( b \\). 由题意，\\( F_1O = c = \\sqrt{a^2 - b^2} \\) \\( (c>0) \\), \\( F_2O = c \\).  \n由于\\(F_2\\)在椭圆上，所以\\(F_2O = a \\).  所以 \\(a = c \\), 且 \\( a = 1 \\).\n又\\( |AF_2| = 2|F_2B| \\) ，\\( |AB| = |BF_1| \\),可以利用椭圆的定义以及两弦性质推导出 \\( b = \\frac{1}{\\sqrt{2}} \\).\n\n从而椭圆的方程为 \\( \\frac{x^2}{2} + y^2 = 1 \\).",
            "解法二：\n利用椭圆的标准方程 \\( \\frac{x^2}{a^2} + \\frac{y^2}{b^2} = 1 \\), \\( F_1(-c,0), F_2(c,0) \\) ，且 \\( c^2 = a^2 - b^2 \\).\n\n首先根据题意，直线过 \\(F_2\\) 和椭圆相交于 \\(A、B\\)两点，可以利用焦点特性得到 \\( \\frac{|SF_2|}{|SA|} = 2 \\) 和 \\( \\frac{|SF_2|}{|SB|} = \\frac{|AB|}{|BF_1|} = \\frac{1}{2} \\)\n\n然后根据椭圆的性质，可以得到 \\( |AF_2| + |BF_2| = 2a = 2|F_2O| \\) 和 \\( |AB| = 2c \\)\n\n通过上述方程组和椭圆参数的定义关系，可以解出 \\( a^2 = 2 \\) 和 \\( b^2 = \\frac{1}{2} \\) \n\n\n从而得到椭圆的方程为 \\( \\frac{x^2}{2} + y^2 = 1 \\)."
        ],
        "response": "解法一：\n设椭圆的中心为 \\( O \\)，半长轴为 \\( a \\)，半短轴为 \\( b \\). 由题意，\\( F_1O = c = \\sqrt{a^2 - b^2} \\) \\( (c>0) \\), \\( F_2O = c \\).  \n由于\\(F_2\\)在椭圆上，所以\\(F_2O = a \\).  所以 \\(a = c \\), 且 \\( a = 1 \\).\n又\\( |AF_2| = 2|F_2B| \\) ，\\( |AB| = |BF_1| \\),可以利用椭圆的定义以及两弦性质推导出 \\( b = \\frac{1}{\\sqrt{2}} \\).\n\n从而椭圆的方程为 \\( \\frac{x^2}{2} + y^2 = 1 \\).\n\n解法二：\n利用椭圆的标准方程 \\( \\frac{x^2}{a^2} + \\frac{y^2}{b^2} = 1 \\), \\( F_1(-c,0), F_2(c,0) \\) ，且 \\( c^2 = a^2 - b^2 \\).\n\n首先根据题意，直线过 \\(F_2\\) 和椭圆相交于 \\(A、B\\)两点，可以利用焦点特性得到 \\( \\frac{|SF_2|}{|SA|} = 2 \\) 和 \\( \\frac{|SF_2|}{|SB|} = \\frac{|AB|}{|BF_1|} = \\frac{1}{2} \\)\n\n然后根据椭圆的性质，可以得到 \\( |AF_2| + |BF_2| = 2a = 2|F_2O| \\) 和 \\( |AB| = 2c \\)\n\n通过上述方程组和椭圆参数的定义关系，可以解出 \\( a^2 = 2 \\) 和 \\( b^2 = \\frac{1}{2} \\) \n\n\n从而得到椭圆的方程为 \\( \\frac{x^2}{2} + y^2 = 1 \\).\n\n\n\n",
        "response_time": 6.870631217956543,
        "id": 3,
        "num": 2
    },
    {
        "question": "如下有一道题目，请一题多解该题目，每个解之间请只用换行符分开，并在开头注明解法几：\n已知三棱锥 \\( P -ABC $ 的四个顶点在球 \\( O $ 的球面上，\\( PA = PB = PC $，△\\( ABC $ 是边长为 \\( 2 $ 的正三角形，\\( E $，\\( F $ 分别是 \\( PA $，\\( PB $ 的中点，∠\\( CEF $=90°，则球 \\( O $ 的体积为\n\\[ \\begin{cases}\n    8\\sqrt{6}\\pi \\\\\n    4\\sqrt{6}\\pi \\\\\n    2\\sqrt{6}\\pi \\\\\n    \\sqrt{6}\\pi\n\\end{cases} \\]\nA．$8\\sqrt{6}\\pi$ & B．$4\\sqrt{6}\\pi$ & C．$2\\sqrt{6}\\pi$ & D．$\\sqrt{6}\\pi$\n",
        "answer": [
            "解法一：\n连接 \\( PO \\) ，作 \\( PO \\) 的垂足 \\( H \\) 到平面 \\( ABC \\) 。由于 \\( PA = PB = PC \\)，所以 \\( H \\) 是 \\( ABC \\) 的内心，也是重心。则 \\( CH = \\frac{2}{3} \\cdot \\frac{2 \\sqrt {3}}{2} = \\frac{2 \\sqrt {3}}{3} \\). \n又由勾股定理， \\( OH = \\sqrt {6} - \\frac{2 \\sqrt {3}}{3} \\), \\( 因此球体半径 R = OH = \\sqrt {6} - \\frac{2 \\sqrt {3}}{3} \\), 球体积为 $\\frac{4}{3} \\pi R^3 = \\frac{4}{3} \\pi \\left(\\sqrt{6} - \\frac{2\\sqrt{3}}{3}\\right)^3 = \\boxed{8\\sqrt{6}\\pi}$",
            "解法二：\n由于 \\( PA = PB = PC \\) ，\\( O \\) 是球心，所以 \\( OP = OB = OC \\)。 \n又 \\( E \\) , \\( F \\) 分别是 \\( PA \\) , \\( PB \\) 的中点，所以 \\( PE = PF = \\frac{PA}{2} \\) 。 \n\\( CEF \\) 是直角三角形，所以 \\(  CF = \\sqrt{CE^2 + EF^2} = \\sqrt{ \\left( \\frac{PA \\sqrt{3}}{2} \\right)^2 + \\left( \\frac{PA}{2} \\right)^2} = \\frac{PA \\sqrt{3}}{2} \\cdot \\sqrt{ \\frac{3}{3+1}} = \\frac{PA\\sqrt{3}}{2} \\cdot \\frac{\\sqrt{3}}{\\sqrt{4}} = \\frac{PA^2}{2\\sqrt{3}} \\) \n\n\\( OP = OB = OC = \\sqrt{OE^2 + PE^2} = \\sqrt{\\left(\\frac{PA}{2}\\right)^2 + \\left(\\frac{PA}{2}\\right)^2} = \\frac{PA \\sqrt{2}}{2}\\)\n\n因为 \\( OABC \\) 是正四面体，所以我们可以用 \\( ABC \\) 的周长 和 \\( AC \\) 的长 度来说明 \\( O \\) 到 \\( ABC \\) 的中点 \\( H \\) 的距离： \\( OH = \\frac{\\sqrt{6}}{3} \\cdot AC = \\frac{\\sqrt{6}}{3} \\cdot 2\\sqrt{3} = 2\\).\\ ( \\( AC = PA = 2\\sqrt{3} \\) )\n\n那么 \\( OP = OH = 2 \\) ，球体积为 $\\frac{4}{3} \\pi (2)^3 = \\boxed{8\\sqrt{6}\\pi}$"
        ],
        "response": "解法一：\n连接 \\( PO \\) ，作 \\( PO \\) 的垂足 \\( H \\) 到平面 \\( ABC \\) 。由于 \\( PA = PB = PC \\)，所以 \\( H \\) 是 \\( ABC \\) 的内心，也是重心。则 \\( CH = \\frac{2}{3} \\cdot \\frac{2 \\sqrt {3}}{2} = \\frac{2 \\sqrt {3}}{3} \\). \n又由勾股定理， \\( OH = \\sqrt {6} - \\frac{2 \\sqrt {3}}{3} \\), \\( 因此球体半径 R = OH = \\sqrt {6} - \\frac{2 \\sqrt {3}}{3} \\), 球体积为 $\\frac{4}{3} \\pi R^3 = \\frac{4}{3} \\pi \\left(\\sqrt{6} - \\frac{2\\sqrt{3}}{3}\\right)^3 = \\boxed{8\\sqrt{6}\\pi}$\n\n解法二：\n由于 \\( PA = PB = PC \\) ，\\( O \\) 是球心，所以 \\( OP = OB = OC \\)。 \n又 \\( E \\) , \\( F \\) 分别是 \\( PA \\) , \\( PB \\) 的中点，所以 \\( PE = PF = \\frac{PA}{2} \\) 。 \n\\( CEF \\) 是直角三角形，所以 \\(  CF = \\sqrt{CE^2 + EF^2} = \\sqrt{ \\left( \\frac{PA \\sqrt{3}}{2} \\right)^2 + \\left( \\frac{PA}{2} \\right)^2} = \\frac{PA \\sqrt{3}}{2} \\cdot \\sqrt{ \\frac{3}{3+1}} = \\frac{PA\\sqrt{3}}{2} \\cdot \\frac{\\sqrt{3}}{\\sqrt{4}} = \\frac{PA^2}{2\\sqrt{3}} \\) \n\n\\( OP = OB = OC = \\sqrt{OE^2 + PE^2} = \\sqrt{\\left(\\frac{PA}{2}\\right)^2 + \\left(\\frac{PA}{2}\\right)^2} = \\frac{PA \\sqrt{2}}{2}\\)\n\n因为 \\( OABC \\) 是正四面体，所以我们可以用 \\( ABC \\) 的周长 和 \\( AC \\) 的长 度来说明 \\( O \\) 到 \\( ABC \\) 的中点 \\( H \\) 的距离： \\( OH = \\frac{\\sqrt{6}}{3} \\cdot AC = \\frac{\\sqrt{6}}{3} \\cdot 2\\sqrt{3} = 2\\).\\ ( \\( AC = PA = 2\\sqrt{3} \\) )\n\n那么 \\( OP = OH = 2 \\) ，球体积为 $\\frac{4}{3} \\pi (2)^3 = \\boxed{8\\sqrt{6}\\pi}$\n\n\n\n",
        "response_time": 8.969738960266113,
        "id": 4,
        "num": 2
    },
    {
        "question": "如下有一道题目，请一题多解该题目，每个解之间请只用换行符分开，并在开头注明解法几：\n13．曲线 \\( y = 3(x^2 + x)e^{-x} $ 在点 $(0,0)$ 处的切线方程为 ____________．",
        "answer": [
            "解法一：\n\n首先求出曲线在点 $(0,0)$ 的导数。\n\n$$\ny' = 3[(2x+1)e^{-x} + (x^2+x)(-e^{-x})] = 3e^{-x}(2x+1-x^2-x) = 3e^{-x}(x+1-x^2)\n$$\n\n在点 $(0,0)$ 处的导数为：\n\n$$\ny'(0) = 3e^0(0+1-0^2) = 3\n$$\n\n因此，在点 $(0,0)$ 处的切线的斜率为 3。 \n\n利用点斜式，切线方程为: \n\n$$\ny-0 = 3(x-0)\n$$\n\n简化得到：\n\n$$\ny = 3x\n$$",
            "解法二：\n\n将曲线方程写为隐式形式： $y = 3(x^2 + x)e^{-x}$。  在点 $(0,0)$ 处，隐式求导：\n\n$$\n\\frac{dy}{dx} = \\frac{d}{dx}[3(x^2 + x)e^{-x}] \n$$\n\n运用乘积规则和链式规则：\n\n$$\n\\frac{dy}{dx} = 3[ (2x+1)e^{-x} + (x^2+x)(-e^{-x})] = 3e^{-x}(x+1-x^2)\n$$\n\n在点 $(0,0)$ 处， $\\frac{dy}{dx} = 3$.  \n\n  利用点斜式，切线方程为: \n$$\ny-0 = 3(x-0)\n$$\n\n简化得到：\n\n$$\ny = 3x\n$$"
        ],
        "response": "解法一：\n\n首先求出曲线在点 $(0,0)$ 的导数。\n\n$$\ny' = 3[(2x+1)e^{-x} + (x^2+x)(-e^{-x})] = 3e^{-x}(2x+1-x^2-x) = 3e^{-x}(x+1-x^2)\n$$\n\n在点 $(0,0)$ 处的导数为：\n\n$$\ny'(0) = 3e^0(0+1-0^2) = 3\n$$\n\n因此，在点 $(0,0)$ 处的切线的斜率为 3。 \n\n利用点斜式，切线方程为: \n\n$$\ny-0 = 3(x-0)\n$$\n\n简化得到：\n\n$$\ny = 3x\n$$\n\n\n解法二：\n\n将曲线方程写为隐式形式： $y = 3(x^2 + x)e^{-x}$。  在点 $(0,0)$ 处，隐式求导：\n\n$$\n\\frac{dy}{dx} = \\frac{d}{dx}[3(x^2 + x)e^{-x}] \n$$\n\n运用乘积规则和链式规则：\n\n$$\n\\frac{dy}{dx} = 3[ (2x+1)e^{-x} + (x^2+x)(-e^{-x})] = 3e^{-x}(x+1-x^2)\n$$\n\n在点 $(0,0)$ 处， $\\frac{dy}{dx} = 3$.  \n\n  利用点斜式，切线方程为: \n$$\ny-0 = 3(x-0)\n$$\n\n简化得到：\n\n$$\ny = 3x\n$$ \n\n\n\n\n\n",
        "response_time": 5.954033136367798,
        "id": 5,
        "num": 2
    },
    {
        "question": "如下有一道题目，请一题多解该题目，每个解之间请只用换行符分开，并在开头注明解法几：\n14．记 \\( S_n $ 为等比数列 $\\left\\{a_n\\right\\}$ 的前 \\( n $ 项和． 若 \\( a_1=\\frac{1}{3} $， \\( a_4^2=a_6 $， 则 \\( S_5=$______________．",
        "answer": [
            "解法一：\n\n根据等比数列性质，\\(a_n=a_1q^{n-1}\\)，其中 \\(q\\) 为公比。 \n\n由 \\(a_4^2=a_6\\)，有 \\(a_1^2q^{6}=a_1q^5\\), 所以 \\(q= \\frac{1}{a_1}=3\\).\n\n则 \\(a_5=a_1q^4=\\frac{1}{3}\\cdot3^4=27\\)\n\n因此 \\(S_5=\\frac{a_1(q^5-1)}{q-1}=\\frac{\\frac{1}{3}(3^5-1)}{3-1}=\\frac{1}{3}\\cdot\\frac{242}{2}=\\boxed{40.33}\\).",
            "解法二：\n\n设公共比为 \\(q\\)，则有\\( a_4=aq^3\\) 和 \\(a_6=aq^5\\), 其中 \\(a=a_1=\\frac{1}{3}\\).\n\n由 \\(a_4^2=a_6\\), 则 \\(a^2q^6=aq^5\\), 即 \\(aq^5=a^2q^6\\).\n\n因为 \\(a\\neq 0\\),所以 \\(q=1/a=3\\).\n\n\\(S_5=\\frac{a(q^5-1)}{q-1}=\\frac{\\frac{1}{3}(3^5-1)}{3-1}=\\frac{1}{3}\\cdot\\frac{242}{2}=\\boxed{40.33}\\)."
        ],
        "response": "解法一：\n\n根据等比数列性质，\\(a_n=a_1q^{n-1}\\)，其中 \\(q\\) 为公比。 \n\n由 \\(a_4^2=a_6\\)，有 \\(a_1^2q^{6}=a_1q^5\\), 所以 \\(q= \\frac{1}{a_1}=3\\).\n\n则 \\(a_5=a_1q^4=\\frac{1}{3}\\cdot3^4=27\\)\n\n因此 \\(S_5=\\frac{a_1(q^5-1)}{q-1}=\\frac{\\frac{1}{3}(3^5-1)}{3-1}=\\frac{1}{3}\\cdot\\frac{242}{2}=\\boxed{40.33}\\).\n\n解法二：\n\n设公共比为 \\(q\\)，则有\\( a_4=aq^3\\) 和 \\(a_6=aq^5\\), 其中 \\(a=a_1=\\frac{1}{3}\\).\n\n由 \\(a_4^2=a_6\\), 则 \\(a^2q^6=aq^5\\), 即 \\(aq^5=a^2q^6\\).\n\n因为 \\(a\\neq 0\\),所以 \\(q=1/a=3\\).\n\n\\(S_5=\\frac{a(q^5-1)}{q-1}=\\frac{\\frac{1}{3}(3^5-1)}{3-1}=\\frac{1}{3}\\cdot\\frac{242}{2}=\\boxed{40.33}\\). \n\n\n",
        "response_time": 5.379899978637695,
        "id": 6,
        "num": 2
    },
    {
        "question": "如下有一道题目，请一题多解该题目，每个解之间请只用换行符分开，并在开头注明解法几：\n甲、乙两队进行篮球决赛，采取七场四胜制（当一队赢得四场胜利时，该队获胜，决赛  \n结束）．根据前期比赛成绩，甲队的主客场安排依次为“主主客客主客主”．设甲队主场取\n胜的概率为0.6，客场取胜的概率为0.5，且各场比赛结果相互独立，则甲队以4∶1获胜的概\n率是____________\n",
        "answer": [
            "解法一：\n\n直接计算甲队在规定的主客场安排下获胜的概率。\n* 主场胜场概率：0.6 * 3 = 1.8\n* 客场胜场概率：0.5 * 2 = 1\n\n甲队需要4场胜利，因此概率为：\n(0.6^3 * 0.5^2) = 0.09",
            "解法二：\n\n使用组合数学求解。\n* 甲队需要赢得4场，乙队需要赢得1场，这可以通过组合数 ${7\\choose4}$  表示，即 35 种可能的比赛结果\n* 只有在甲队赢得4场且乙队赢得1场的情况下，甲队才能以4:1获胜。\n* 因此，甲队以4:1获胜的概率为：${35\\choose4} \\times (0.6^4) \\times (0.5^3)$"
        ],
        "response": "解法一：\n\n直接计算甲队在规定的主客场安排下获胜的概率。\n* 主场胜场概率：0.6 * 3 = 1.8\n* 客场胜场概率：0.5 * 2 = 1\n\n甲队需要4场胜利，因此概率为：\n(0.6^3 * 0.5^2) = 0.09\n\n解法二：\n\n使用组合数学求解。\n* 甲队需要赢得4场，乙队需要赢得1场，这可以通过组合数 ${7\\choose4}$  表示，即 35 种可能的比赛结果\n* 只有在甲队赢得4场且乙队赢得1场的情况下，甲队才能以4:1获胜。\n* 因此，甲队以4:1获胜的概率为：${35\\choose4} \\times (0.6^4) \\times (0.5^3)$\n\n\n",
        "response_time": 3.621340274810791,
        "id": 7,
        "num": 2
    },
    {
        "question": "如下有一道题目，请一题多解该题目，每个解之间请只用换行符分开，并在开头注明解法几：\n16．已知双曲线 \\( C $：$\\frac{x^2}{a^2}-\\frac{y^2}{b^2}=1(a>0,b>0)$ 的左、右焦点分别为 \\( F_1 $，\\( F_2 $，过 \\( F_1 $ 的直线与 \\( C $ 的两条渐近线分别交于 \\( A $，\\( B $ 两点．若 \\( \\overrightarrow{{F}_{1}A}=\\overrightarrow{AB} $，\\( \\overrightarrow{{F}_{1}B}⋅\\overrightarrow{{F}_{2}B}=0 $，则 \\( C $ 的离心率为 ____________．\n",
        "answer": [
            "解法一：\n\n根据题目的条件，我们可以推出  \\( \\overrightarrow{F_1A} = \\overrightarrow{AB} \\) 这意味着点 \\(A\\)关于 \\(F_2\\) 镜面对称。进一步推导出 \\( F_1 \\)  \\( A \\)  \\( B \\) 三点共线。\n\n由于 \\( \\overrightarrow{{F}_{1}B} \\cdot \\overrightarrow{{F}_{2}B} = 0 \\)  ， 意味着 \\( \\overrightarrow{F_1B} \\)  垂直于 \\( \\overrightarrow{F_2B} \\)  ， 这意味着  \\( F_1 \\) \\  \\( B \\)  \\( F_2 \\) 三点共线。\n\n结合上述两条，我们可以得知 \\( A \\)  \\( B \\)  \\( F_1 \\)  \\( F_2 \\) 四点共线。\n\n由于 \\( A \\)  和 \\( B \\)  分别为双曲线 \\(C\\) 的渐近线和 \\( F_1 \\) 的外侧交点，所以 \\( AB \\)  是双曲线的渐近线互相垂直的交线。\n\n根据双曲线的性质，渐近线方程为 \\( y = \\pm \\frac{b}{a}x \\)  。因为 \\( AB \\)  通过点 \\(F_1\\)  ， 我们可以列出方程组来求解 \\( a \\) 和 \\( b \\) 的值。\n\n最后，利用离心率公式 \\( e=\\sqrt{1+\\frac{b^2}{a^2}} \\)  即可求解。",
            "解法二：\n\n\n解法三："
        ],
        "response": "解法一：\n\n根据题目的条件，我们可以推出  \\( \\overrightarrow{F_1A} = \\overrightarrow{AB} \\) 这意味着点 \\(A\\)关于 \\(F_2\\) 镜面对称。进一步推导出 \\( F_1 \\)  \\( A \\)  \\( B \\) 三点共线。\n\n由于 \\( \\overrightarrow{{F}_{1}B} \\cdot \\overrightarrow{{F}_{2}B} = 0 \\)  ， 意味着 \\( \\overrightarrow{F_1B} \\)  垂直于 \\( \\overrightarrow{F_2B} \\)  ， 这意味着  \\( F_1 \\) \\  \\( B \\)  \\( F_2 \\) 三点共线。\n\n结合上述两条，我们可以得知 \\( A \\)  \\( B \\)  \\( F_1 \\)  \\( F_2 \\) 四点共线。\n\n由于 \\( A \\)  和 \\( B \\)  分别为双曲线 \\(C\\) 的渐近线和 \\( F_1 \\) 的外侧交点，所以 \\( AB \\)  是双曲线的渐近线互相垂直的交线。\n\n根据双曲线的性质，渐近线方程为 \\( y = \\pm \\frac{b}{a}x \\)  。因为 \\( AB \\)  通过点 \\(F_1\\)  ， 我们可以列出方程组来求解 \\( a \\) 和 \\( b \\) 的值。\n\n最后，利用离心率公式 \\( e=\\sqrt{1+\\frac{b^2}{a^2}} \\)  即可求解。\n\n解法二：\n\n\n解法三：\n\n\n\n",
        "response_time": 5.707021474838257,
        "id": 8,
        "num": 2
    },
    {
        "question": "如下有一道题目，请一题多解该题目，每个解之间请只用换行符分开，并在开头注明解法几：\n17．$\\triangle ABC $ 的内角 \\( A $，\\( B $，\\( C $ 的对边分别为 \\( a $，\\( b $，\\( c $， 设\n\\[ (\\sin B-\\sin C)^2=sin^2 A-sin B sin C $．\n\\[ （1）求 \\( A $；\n\\[ （2）若 $\\sqrt{2a+b}=2c $， 求 \\( sin C $.\n\n",
        "answer": [],
        "response": "## 解法一\n (1) 利用三角函数的正弦差公式 \n $(\\sin B - \\sin C)^2 = \\sin^2 B - 2 \\sin B \\sin C + \\sin^2 C$，\n将这个式子代入原式，得到：\n\\[\\sin^2 B - 2 \\sin B \\sin C + \\sin^2 C = \\sin^2 A - \\sin B \\sin C.\\]\n整理, 得到：\\( \\sin^2 B + \\sin^2 C - \\sin^2 A = \\sin B \\sin C \\).\n利用三角形内角和定理 \\( \\sin^2 A + \\sin^2 B + \\sin^2 C = 1\\) 可得：\n\\[\\sin^2 A = 1 - \\sin^2 B - \\sin^2 C = 1 - (\\sin^2 B + \\sin^2 C).\\]\n将这个式子代入上式：\n\\[1 - (\\sin^2 B + \\sin^2 C) = \\sin B \\sin C.\\]\n进一步整理, 得到 \\( \\sin^2 B + \\sin^2 C + \\sin B \\sin C - 1 = 0 \\).\n这个方程是关于 \\( \\sin B \\) 和 \\( \\sin C \\) 的二次方程，可以利用解二次方程的公式求解。\n然而，这个过程比较繁琐，我们有一条简便的解法。\n\n(2) 利用 $\\sqrt{2a+b}=2c$，根据余弦定理，我们有：\n\\[c^2 = a^2 + b^2 - 2ab \\cos C.\\]\n平方两边，得到：\\(4c^2 = 4a^2 + 4b^2 - 8ab \\cos C \\).\n又因为 $\\sqrt{2a+b}=2c$, 所以 $2a+b = 4c^2$，代入上式并化简，可以得到关于 \\( \\cos C \\) 的方程。\n接着利用三角函数恒等式 \\( \\sin^2 C + \\cos^2 C = 1\\) 解出 \\( \\sin C \\).\n\n## 解法二\n(1)  利用正弦定理，可得：\n\n\\[\\frac{a}{\\sin A} = \\frac{b}{\\sin B} = \\frac{c}{\\sin C} = k.\\]\n所以, \\(a = k \\sin A\\), \\(b = k \\sin B\\), \\(c = k \\sin C\\).\n\n将这个式子代入原式 \\((\\sin B - \\sin C)^2 = \\sin^2 A - \\sin B \\sin C\\) 后，整理得到一个关于 \\( \\sin A \\) 的方程，并求解即可。\n\n(2) 利用 $\\sqrt{2a+b}=2c$，和正弦定理，根据上述步骤将 \\( \\sin A \\) 和 \\( \\sin B \\) 与 \\( \\sin C \\) 做关联，最终解出 \\( \\sin C \\).\n\n\n\n\n",
        "response_time": 9.616449117660522,
        "id": 9,
        "num": 0
    },
    {
        "question": "如下有一道题目，请一题多解该题目，每个解之间请只用换行符分开，并在开头注明解法几：\n19．已知抛物线 \\( C $：$y^2=3x$ 的焦点为 \\( F $， 斜率为$-\\frac{3}{2}$ 的直线 \\( l $ 与 \\( C $ 的交点为 \\( A $，\\( B $， 与x轴的交点为 \\( P $．\n\\[ （1）若 \\( |AF|+|BF|=4 $，求 \\( l $ 的方程；\n\\[ （2）若 $\\overrightarrow{AP}=3\\overrightarrow{PB}$， 求 \\( |AB|$．\n",
        "answer": [],
        "response": "## 解法一\n\n**(1)**  抛物线 \\(C\\) 的焦点为 \\(F\\left(\\frac{3}{4},0\\right)\\) . 设直线 \\(l\\) 的方程为 \\(y=kx-\\frac{3}{2}x+c\\), 则 \n $$|AF| + |BF| = \\sqrt{\\left(x_A - \\frac{3}{4}\\right)^2 + (y_A - 0)^2} + \\sqrt{\\left(x_B - \\frac{3}{4}\\right)^2 + (y_B - 0)^2} = 4$$ \n  因为 \\(A\\) 和 \\(B\\) 在抛物线上, 所以 \\(y_A^2 = 3x_A\\) 和 \\(y_B^2 = 3x_B\\). 将 \\(y_A\\) 和 \\(y_B\\) 代入直线 \\(l\\) 方程，并化简后得到关于 \\(x_A\\), \\(x_B\\) 的方程， 结合 \\( |AF| + |BF|=4\\)  条件，求解 \\(x_A \\), \\(x_B\\) 以及 \\(c\\),  即可得到直线 \\(l\\) 的方程.\n \n **(2)** 因为 $\\overrightarrow{AP}=3\\overrightarrow{PB}$, 所以 \\(\\frac{x_P-x_A}{x_P-x_B}=3\\). 同时,  \\(x_P\\) 是直线 \\(l\\) 在 x 轴上的交点, 可以由直线方程解出. 利用 \\(x_P\\) 和点 \\(A\\), \\(B\\) 的坐标取得 \\(AB\\) 的长度即可.\n\n\n \n\n\n## 解法二 \n\n**(1)** 由于抛物线的对称轴为 x 轴，因此 \\(A\\) 和 \\(B\\) 在对称轴的两侧. 由题意，\\( |AF|+|BF|=4 \\) 意味着 \\(A\\), \\(B\\) 分别位于焦点 \\(F\\) 与抛物线关于对称轴的对称两端. \n定义 \\(P\\) 为对称轴与直线 \\(l\\) 的交点， 则 \\(\\overrightarrow{AP}= \\overrightarrow{PF_1}\\), \\(  \\overrightarrow{FB}=\\overrightarrow{PF_2} \\), 其中 \\(F_1 \\), \\(F_2\\) 是 \\(F\\) 关于 \\(l\\) 的对称点.\n 利用旋转不变性定理，我们可以证明 \\(l\\) 的方程与 \\(F_1 \\), \\(F_2\\) 以及 \\(P\\) 的坐标成正比关系.\n\n\n**(2)** 利用 (1) 中的结论，我们可以将 \\(AB\\) 在对称轴上的投影长度和 \\(PF_1\\), \\(PF_2\\) 的长度联系起来. 通过几何计算和坐标变换，就可以求出 \\(|AB|\\). \n\n\n\n \n\n\n\n",
        "response_time": 9.115636348724365,
        "id": 10,
        "num": 0
    },
    {
        "question": "如下有一道题目，请一题多解该题目，每个解之间请只用换行符分开，并在开头注明解法几：\n20．已知函数 \\( f(x)=sin x-ln(1+x) $， \\( f'(x) $ 为 \\( f(x) $ 的导数．证明：\n\\[ （1）f'(x) $ 在区间$ (-1,\\frac{\\pi}{2}) $存在唯一极大值点；\n\\[ （2）\\( f(x) $有且仅有2个零点．\n",
        "answer": [
            "解法一：\n1.  先求出 \\(f'(x)\\)：\n\n\\( f'(x) = cos x - \\frac{1}{1+x} \\)\n\n2.  研究 \\(f'(x)\\) 的单调性在 (-1, π/2) 区间内。\n\n* \\(cos x\\) 在 (-1, π/2) 上单调递减。\n* \\( \\frac{1}{1+x}  \\) 在 (-1, π/2) 上单调递增。\n\n因此，\\(f'(x)\\) 在 (-1, π/2) 区间内先递减后递增，也就是说在 (-1, π/2) 区间内存在唯一的一个极大值点。\n3.  利用导数零点确定极大值点：\n\n令 \\(f'(x) = 0\\)，得到：\n\n\\( cos x - \\frac{1}{1+x} = 0 \\)\n\n解方程可得唯一解属于 (-1, π/2) 区间。\n\n4.  利用间值定理证明\\( f(x) $有且仅有 2 个零点：\n\n*  \\(f(x)\\) 的定义域为 (-1, +∞) 。\n*  给定 \\(x\\)  在区间 (-1, 0) 范围内，\\( f(x) \\)  必为负数，因为 \\(sin x < 0\\) 且  \\(ln(1+x) > 0\\) 。\n*  给定 \\(x\\) 在区间 (0, +∞) 范围内，\\( f(x) \\) 存在正值。并且由于 \\(f'(x)\\) 在 (-1, π/2) 存在唯一极大值点，所以 \\(f(x)\\) 在该区间内单调增加。\n*  根据连续性，\\(f(x)\\) 必定穿过横轴两次，即有且仅有2个零点。",
            "解法二：\n1. 分析 \\(f(x)\\) 的性质:\n    * \\(  sin x \\)在 (-1, π/2) 上单调递增。\n    * \\( ln(1+x) \\) 在 (-1, +∞) 上单调递增。\n\n2. 根據 \\(f(x)\\) 的性质, \\(f'(x)\\) 在 (-1, π/2) 区间内首先单调递减， 然后单调递增， 因此在该区间内存在唯一极大值点。\n\n3. 证明\\(f(x)\\) 的零点个数：\n    *  \\(f(0) = 0 \\) ，所以  \\(f(x)\\) 至少有一个零点。\n    * \\(f(x) \\) 在 (-1, 0) 范围内恒为负， 在 (π/2, +∞) 范围内恒为正， 因此 \\(f(x)\\) 只能穿过横轴一次。\n    *  根据连续性，\\(f(x)\\) 有且仅有 2 个零点。"
        ],
        "response": "解法一：\n1.  先求出 \\(f'(x)\\)：\n\n\\( f'(x) = cos x - \\frac{1}{1+x} \\)\n\n2.  研究 \\(f'(x)\\) 的单调性在 (-1, π/2) 区间内。\n\n* \\(cos x\\) 在 (-1, π/2) 上单调递减。\n* \\( \\frac{1}{1+x}  \\) 在 (-1, π/2) 上单调递增。\n\n因此，\\(f'(x)\\) 在 (-1, π/2) 区间内先递减后递增，也就是说在 (-1, π/2) 区间内存在唯一的一个极大值点。\n3.  利用导数零点确定极大值点：\n\n令 \\(f'(x) = 0\\)，得到：\n\n\\( cos x - \\frac{1}{1+x} = 0 \\)\n\n解方程可得唯一解属于 (-1, π/2) 区间。\n\n4.  利用间值定理证明\\( f(x) $有且仅有 2 个零点：\n\n*  \\(f(x)\\) 的定义域为 (-1, +∞) 。\n*  给定 \\(x\\)  在区间 (-1, 0) 范围内，\\( f(x) \\)  必为负数，因为 \\(sin x < 0\\) 且  \\(ln(1+x) > 0\\) 。\n*  给定 \\(x\\) 在区间 (0, +∞) 范围内，\\( f(x) \\) 存在正值。并且由于 \\(f'(x)\\) 在 (-1, π/2) 存在唯一极大值点，所以 \\(f(x)\\) 在该区间内单调增加。\n*  根据连续性，\\(f(x)\\) 必定穿过横轴两次，即有且仅有2个零点。\n\n\n\n\n解法二：\n1. 分析 \\(f(x)\\) 的性质:\n    * \\(  sin x \\)在 (-1, π/2) 上单调递增。\n    * \\( ln(1+x) \\) 在 (-1, +∞) 上单调递增。\n\n2. 根據 \\(f(x)\\) 的性质, \\(f'(x)\\) 在 (-1, π/2) 区间内首先单调递减， 然后单调递增， 因此在该区间内存在唯一极大值点。\n\n3. 证明\\(f(x)\\) 的零点个数：\n    *  \\(f(0) = 0 \\) ，所以  \\(f(x)\\) 至少有一个零点。\n    * \\(f(x) \\) 在 (-1, 0) 范围内恒为负， 在 (π/2, +∞) 范围内恒为正， 因此 \\(f(x)\\) 只能穿过横轴一次。\n    *  根据连续性，\\(f(x)\\) 有且仅有 2 个零点。  \n\n\n\n\n\n\n",
        "response_time": 9.608750104904175,
        "id": 11,
        "num": 2
    },
    {
        "question": "如下有一道题目，请一题多解该题目，每个解之间请只用换行符分开，并在开头注明解法几：\n21．为了治疗某种疾病，研制了甲、乙两种新药，希望知道哪种新药更有效，为此进行动物试验．试验方案如下：每一轮选取两只白鼠对药效进行对比试验．对于两只白鼠，随机选一只施以甲药，另一只施以乙药．一轮的治疗结果得出后，再安排下一轮试验．当其中一种药治愈的白鼠比另一种药治愈的白鼠多4只时，就停止试验，并认为治愈只数多的药更有效．为了方便描述问题，约定：对于每轮试验，若施以甲药的白鼠治愈且施以乙药的白鼠未治愈则甲药得1分，乙药得−1分；若施以乙药的白鼠治愈且施以甲药的白鼠未治愈则乙药得1分，甲药得−1分；若都治愈或都未治愈则两种药均得0分．甲、乙两种药的治愈率分别记为 \\( α $和 \\( β $，一轮试验中甲药的得分记为 \\( X $．\n\\[ （1）求 \\( X $的分布列；\n\\[ （2）若甲药、乙药在试验开始时都赋予4分， \\( p_i(i=0,1,…,8) $表示“甲药的累计得分为 \\( i $时最终认为甲药比乙药更有效”的概率，则 \\( p_0=0 $， \\( p_8=1 $， \\( p_i=aP(X=-1)+bP(X=0)+cP(X=1) $（\\( i=1,2,…,7），其中 \\( a=P(X=-1)， \\( b=P(X=0)， \\( c=P(X=1) $．假设 \\( α=0.5 $， \\( β=0.8 $．\n\\[ （i）证明： \\( {p}_{i+1}-{p}_{i}(i=0,1,2,…,7) $为等比数列；\n\\[ （ii）求 \\( p_4 $，并根据 \\( p_4 $的值解释这种试验方案的合理性．\n",
        "answer": [
            "## 解法一：\n\n(1) 由于每轮试验的结果只与甲、乙药的治愈率有关，所以 X 的可取值为 { -1, 0, 1 } 。\n其分布列为：\n  * P(X = -1) = (1 - α)β  \n  * P(X = 0) = α(1 - β) + (1 - α)β  \n  * P(X = 1) = αβ\n\n(2)  \n(i) \n首先，我们需要求出 \\( p_{i+1}-p_i \\) 的表达式。根据题意，\\( p_i=aP(X=-1)+bP(X=0)+cP(X=1) \\)， 因此：\n\n\\( p_{i+1}-p_i = [aP(X=-1)+bP(X=0)+cP(X=1)] - [aP(X=-1)+bP(X=0)+cP(X=1)] \\)\n\n \n = 0  \n\n这意味着 \\( p_{i+1}-p_i \\) 为等差数列，其值为0。\n\n(ii) \n根据 (1) 中的分布列，代入 α = 0.5, β = 0.8 计算即可得到 p4 的值。",
            "## 解法二： \n\n**注意：** 解法二的推导可能比解法一更复杂，但它利用了概率的基本原理，可以更深入地理解问题的本质。\n\n(1) 利用卷积和概率的基本原理，可以推导出 X 的分布列。 因为每次试验的结果只与两只老鼠的治愈情况有关，  所以可以使用概率树或其他方法来绘制该概率分布。\n\n(2) \n(i) \n\n这个部分与解法一类似， 通过计算\\( p_{i+1}-p_i \\) 的表达式，可以证明其是一个等比数列。\n\n(ii)  \n\n通过求解 \\(p_4\\) 的值，可以观察到该试验方案的合理性。注意到，\n\n * 如果你观察到的\\(p_4\\)很大，则意味着在初期实验中甲药领先优势的概率很大，表明甲药可能更有效。\n * 如果\\(p_4\\) 很小，则意味着甲药和乙药的得分的差别很小，试验结果不具有足够的统计意义。\n\n同时，你需要结合具体的数值来判断试验方案的合理性，例如，是否需要进行更长的试验以获得更可靠的结论。\n\n\n\n希望以上两种解法能够帮助你理解这个问题。 选择哪种解法取决于你的个人偏好和理解能力。"
        ],
        "response": "## 解法一：\n\n(1) 由于每轮试验的结果只与甲、乙药的治愈率有关，所以 X 的可取值为 { -1, 0, 1 } 。\n其分布列为：\n  * P(X = -1) = (1 - α)β  \n  * P(X = 0) = α(1 - β) + (1 - α)β  \n  * P(X = 1) = αβ\n\n(2)  \n(i) \n首先，我们需要求出 \\( p_{i+1}-p_i \\) 的表达式。根据题意，\\( p_i=aP(X=-1)+bP(X=0)+cP(X=1) \\)， 因此：\n\n\\( p_{i+1}-p_i = [aP(X=-1)+bP(X=0)+cP(X=1)] - [aP(X=-1)+bP(X=0)+cP(X=1)] \\)\n\n \n = 0  \n\n这意味着 \\( p_{i+1}-p_i \\) 为等差数列，其值为0。\n\n(ii) \n根据 (1) 中的分布列，代入 α = 0.5, β = 0.8 计算即可得到 p4 的值。\n\n## 解法二： \n\n**注意：** 解法二的推导可能比解法一更复杂，但它利用了概率的基本原理，可以更深入地理解问题的本质。\n\n(1) 利用卷积和概率的基本原理，可以推导出 X 的分布列。 因为每次试验的结果只与两只老鼠的治愈情况有关，  所以可以使用概率树或其他方法来绘制该概率分布。\n\n(2) \n(i) \n\n这个部分与解法一类似， 通过计算\\( p_{i+1}-p_i \\) 的表达式，可以证明其是一个等比数列。\n\n(ii)  \n\n通过求解 \\(p_4\\) 的值，可以观察到该试验方案的合理性。注意到，\n\n * 如果你观察到的\\(p_4\\)很大，则意味着在初期实验中甲药领先优势的概率很大，表明甲药可能更有效。\n * 如果\\(p_4\\) 很小，则意味着甲药和乙药的得分的差别很小，试验结果不具有足够的统计意义。\n\n同时，你需要结合具体的数值来判断试验方案的合理性，例如，是否需要进行更长的试验以获得更可靠的结论。\n\n\n\n希望以上两种解法能够帮助你理解这个问题。 选择哪种解法取决于你的个人偏好和理解能力。",
        "response_time": 8.371335744857788,
        "id": 12,
        "num": 2
    }
]